{
  "document_type": "Hotel Invoice",
  "vendor_name": "KING PARK HOTEL TAWAU",
  "document_number": "3007",
  "document_date": null,
  "currency": "MYR",
  "total_amount": "429.00",
  "bill_to": "Syahrul Nizam Bin Salamon ,\nArena Watsons Level 7 Exchange 106\nLingkaran TRX 55188\n\nKuala Lumpur\n, Kuala Lumpur\n\nMALAYSIA",
  "line_items": [
    {
      "item_number": null,
      "description": "ROOM CHARGE",
      "quantity": null,
      "unit_price": null,
      "Reference / Supporting Information": "702 *",
      "tax": null,
      "amount": "143.00"
    },
    {
      "item_number": null,
      "description": "ROOM CHARGE",
      "quantity": null,
      "unit_price": null,
      "Reference / Supporting Information": "702 *",
      "tax": null,
      "amount": "143.00"
    },
    {
      "item_number": null,
      "description": "ROOM CHARGE",
      "quantity": null,
      "unit_price": null,
      "Reference / Supporting Information": "702 *",
      "tax": null,
      "amount": "143.00"
    }
  ],
  "subtotal": "429.00",
  "tax_total": "31.77",
  "discount": null,
  "freight_charges": null,
  "grand_total": "429.00",
  "amount_in_words": "FOUR HUNDRED TWENTY NINE ONLY",
  "additional_fields": {
    "SSM No. (NEW)": "198501012442",
    "SSM No. (OLD)": "144896-K",
    "SST No.": "S60-1808-31028233",
    "TIN No.": "C8858930100",
    "GUEST NAME": "Syahrul Nizam Bin Salamon ,",
    "INVOICE NO.": "INVOICE No. 3007",
    "CONFIRMATION NO.": "10003155",
    "GUEST/GROUP ID": "0",
    "ROOM NO.": "702",
    "GUEST PAX": "2/0/0",
    "NATIONALITY": "Malaysian",
    "ARRIVE": "11/11/2025 11:51",
    "DEPART": "14/11/2025 04:25",
    "PRINTED BY": "Y2V3 jurayah",
    "Advances (MYR)": "0.00",
    "Net (MYR)": "429.00",
    "Transfer to Debtor Account": "WATSON'S PERSONAL CARE STORE",
    "Tax type": "OTHR | SSTax (FB) | 8.00 | 83.34 | 6.66\nOTHR | SSTax (RM) | 8.00 | 313.89 | 25.11",
    "Date": "14th October, 2025",
    "Watson’s Personal Care Stores Sdn Bhd": "Reg No: 289892 V",
    "Attention": "Reservation Dept (reservations@tawau.kingparkhotel.com.my)",
    "Room Type": "2 Superior Twin Room",
    "Room Rate": "RM143.00nett (2 breakfast)\n(Only room charged to Company)",
    "Check In": "11/11/2025",
    "Check Out": "14/11/2025",
    "Duration": "3 nights",
    "Purpose": "Week 46 – Stocktake at M341, M087, M466 & M2205",
    "Guest Name (Reservation)": "Syahrul Nizam Bin Salamon\nMohd Syafiie Firdaus Bin Mahali\nJonexshon John\nJesua Richard"
  }
}